sim/programs/count.vh
`define TRACE_COUNT 167
`define END_PC 32'd656
`define IMM_COUNT 4120

rtl/Single_Cycle.v
`timescale 1ns/1ps
`default_nettype none
// Harvard, single-cycle RV32I subset. Byte addresses, word-aligned accesses.
module Single_Cycle #(parameter IMEM_WORDS=256, DMEM_WORDS=64,
                      parameter PROGRAM_FILE="sim/programs/demo.hex")
(input wire clk, reset, output reg [31:0] PC,
 output wire [31:0] instruction, ALU_Out, writeback,
 output wire RegWrite, MemWrite, BranchTaken, output wire fault);
 wire [31:0] a,b,imm,alu_b,load_data;
 wire [3:0] alu_op;
 wire use_imm,mem_read,mem_to_reg,branch,jump,legal,zero;
 wire [31:0] next_pc;
 wire if_ok,mem_ok;
 wire [31:0] target=PC+imm;
 assign next_pc=(BranchTaken || jump) ? target : PC+32'd4;
 assign fault=!if_ok || !legal || ((mem_read || MemWrite) && !mem_ok)
              || ((BranchTaken || jump) && target[1:0]!=0);
 assign BranchTaken=branch && zero;
 assign alu_b=use_imm ? imm : b;
 assign writeback=jump ? PC+32'd4 : (mem_to_reg ? load_data : ALU_Out);
 always @(posedge clk or posedge reset)
   if(reset) PC<=0;
   else if(!fault) PC<=next_pc;
 Instruction_Memory #(IMEM_WORDS,PROGRAM_FILE) imem(PC,instruction,if_ok);
 Register_File rf(clk,reset,RegWrite && !fault,instruction[19:15],
                 instruction[24:20],instruction[11:7],writeback,a,b);
 Immediate_Generator ig(instruction,imm);
 Control_Unit cu(instruction,RegWrite,use_imm,mem_read,MemWrite,
                 mem_to_reg,branch,jump,alu_op,legal);
 ALU alu(a,alu_b,alu_op,ALU_Out,zero);
 Data_Memory #(DMEM_WORDS) dmem(clk,reset,MemWrite && !fault,
                               mem_read,ALU_Out,b,load_data,mem_ok);
endmodule

module Instruction_Memory #(parameter WORDS=256, parameter PROGRAM_FILE="sim/programs/demo.hex")
(input wire [31:0] address,output wire [31:0] instruction,output wire valid);
 reg [31:0] mem[0:WORDS-1];
 initial $readmemh(PROGRAM_FILE,mem);
 assign valid=(address[1:0]==0 && address[31:2]<WORDS);
 assign instruction=valid ? mem[address[31:2]] : 32'h00000000;
endmodule

module Register_File(input wire clk,reset,we,input wire [4:0] rs1,rs2,rd,
 input wire [31:0] wd,output wire [31:0] a,b);
 reg [31:0] regs[0:31]; integer i;
 always @(posedge clk or posedge reset)
   if(reset) begin
     for(i=0;i<32;i=i+1) regs[i]<=0;
   end else if(we && rd!=0) regs[rd]<=wd;
 assign a=(rs1==0) ? 32'b0 : regs[rs1];
 assign b=(rs2==0) ? 32'b0 : regs[rs2];
endmodule

module Immediate_Generator(input wire [31:0] ins,output reg [31:0] imm);
 always @* begin
   imm=0;
   case(ins[6:0])
    7'h03,7'h13: imm={{20{ins[31]}},ins[31:20]};
    7'h23: imm={{20{ins[31]}},ins[31:25],ins[11:7]};
    7'h63: imm={{19{ins[31]}},ins[31],ins[7],ins[30:25],ins[11:8],1'b0};
    7'h6f: imm={{11{ins[31]}},ins[31],ins[19:12],ins[20],ins[30:21],1'b0};
    default: imm=0;
   endcase
 end
endmodule

// ALU encoding: ADD,SUB,AND,OR,XOR,SLL,SRL,SRA,SLT,SLTU.
module Control_Unit(input wire [31:0] ins,
 output reg rw,src,mr,mw,mtr,branch,jump,output reg [3:0] op,output reg legal);
 always @* begin
  rw=0;src=0;mr=0;mw=0;mtr=0;branch=0;jump=0;op=0;legal=0;
  case(ins[6:0])
   7'h33,7'h13: begin
    rw=1;src=(ins[6:0]==7'h13);legal=1;
    case(ins[14:12])
     0: begin
      op=0;
      if(!src) begin
       if(ins[31:25]==7'h20) op=1;
       else if(ins[31:25]!=0) legal=0;
      end
     end
     7: op=2;
     6: op=3;
     4: op=4;
     1: begin op=5; if(ins[31:25]!=0) legal=0; end
     5: begin
      if(ins[31:25]==0) op=6;
      else if(ins[31:25]==7'h20) op=7;
      else legal=0;
     end
     2: op=8;
     3: op=9;
     default: legal=0;
    endcase
    if(!src && ins[14:12]!=0 && ins[14:12]!=5 && ins[31:25]!=0) legal=0;
   end
   7'h03: begin src=1;rw=1;mr=1;mtr=1;legal=(ins[14:12]==2);end
   7'h23: begin src=1;mw=1;legal=(ins[14:12]==2);end
   7'h63: begin branch=1;op=1;legal=(ins[14:12]==0);end
   7'h6f: begin jump=1;rw=1;legal=1;end
   default: legal=0;
  endcase
 end
endmodule

module ALU(input wire [31:0] a,b,input wire [3:0] op,
 output reg [31:0] result,output wire zero);
 always @* begin
  case(op)
   0:result=a+b; 1:result=a-b; 2:result=a&b; 3:result=a|b;
   4:result=a^b; 5:result=a<<b[4:0]; 6:result=a>>b[4:0];
   7:result=$signed(a)>>>b[4:0];
   8:result={31'b0,($signed(a)<$signed(b))};
   9:result={31'b0,(a<b)};
   default:result=0;
  endcase
 end
 assign zero=(result==0);
endmodule

module Data_Memory #(parameter WORDS=64)
(input wire clk,reset,we,re,input wire [31:0] address,wd,
 output wire [31:0] data,output wire valid);
 reg [31:0] mem[0:WORDS-1]; integer i;
 assign valid=(address[1:0]==0 && address[31:2]<WORDS);
 always @(posedge clk or posedge reset)
  if(reset) begin for(i=0;i<WORDS;i=i+1) mem[i]<=0;end
  else if(we && valid) mem[address[31:2]]<=wd;
 assign data=(re && valid) ? mem[address[31:2]] : 32'b0;
endmodule
`default_nettype wire

sim/tb_single_cycle.v
`timescale 1ns/1ps
`default_nettype none
`include "sim/programs/count.vh"
module tb_single_cycle;
 reg clk=0,reset=1;
 wire [31:0] pc,ins,alu,wb;
 wire rw,mw,bt,fault;
 reg [255:0] expected[0:`TRACE_COUNT-1];
 reg [31:0] expected_regs[0:31],expected_mem[0:63];
 reg [255:0] row; integer i;
 reg [63:0] imm_vectors[0:`IMM_COUNT-1];
 reg [31:0] probe_ins=0; wire [31:0] probe_imm;
 Immediate_Generator probe(probe_ins,probe_imm);
 Single_Cycle dut(clk,reset,pc,ins,alu,wb,rw,mw,bt,fault);
 always #5 clk=~clk;
 initial begin
  $readmemh("sim/programs/expected.hex",expected);
  $readmemh("sim/programs/immediates.hex",imm_vectors);
  $readmemh("sim/programs/registers.hex",expected_regs);
  $readmemh("sim/programs/memory.hex",expected_mem);
  $dumpfile("results/core.vcd");$dumpvars(0,tb_single_cycle);
  #12;reset=0;
  for(i=0;i<`TRACE_COUNT;i=i+1) begin
   row=expected[i];#1;
   if(fault || pc!==row[255:224]) $fatal(1,"PC/fault mismatch at step %0d PC=%h",i,pc);
   if(rw!==row[128] || mw!==row[64]) $fatal(1,"Control mismatch at step %0d",i);
   if(rw && (ins[11:7]!==row[164:160] || wb!==row[127:96])) $fatal(1,"Writeback mismatch step %0d got %h expected %h",i,wb,row[127:96]);
   if(mw && (alu!==row[63:32] || dut.b!==row[31:0])) $fatal(1,"Store mismatch step %0d",i);
   @(posedge clk);#1;
   if(pc!==row[223:192]) $fatal(1,"Next PC mismatch step %0d",i);
   @(negedge clk);
  end
  if(pc!==`END_PC) $fatal(1,"End PC mismatch");
  for(i=0;i<32;i=i+1) if(dut.rf.regs[i]!==expected_regs[i]) $fatal(1,"Register x%0d mismatch",i);
  for(i=0;i<64;i=i+1) if(dut.dmem.mem[i]!==expected_mem[i]) $fatal(1,"Memory word %0d mismatch",i);
  repeat(3) begin @(posedge clk);#1;if(pc!==`END_PC) $fatal(1,"JAL loop failed");end
  // Inject one instruction while reset is asserted. Check faults have no side effects.
  check_fault(32'hffffffff); // illegal opcode
  check_fault(32'h020000b3); // unsupported MUL encoding
  check_fault(32'h00202083); // misaligned LW
  check_fault(32'h10002083); // out-of-range LW
  check_fault(32'h00002123); // misaligned SW
  check_fault(32'h10002023); // out-of-range SW
  check_fault(32'h0020006f); // misaligned JAL target
  check_fault(32'h00200163); // taken BEQ +2
  reset=1;#1;dut.imem.mem[0]=32'h00000013;#1;reset=0;
  @(negedge clk);dut.PC=32'd1024;#1;
  if(!fault) $fatal(1,"Instruction range guard failed");
  @(posedge clk);#1;if(pc!==1024) $fatal(1,"Fetch fault did not halt");
  for(i=0;i<`IMM_COUNT;i=i+1) begin
   probe_ins=imm_vectors[i][63:32];#1;
   if(probe_imm!==imm_vectors[i][31:0]) $fatal(1,"Immediate mismatch vector %0d",i);
  end
  $display("PASS: %0d immediate extraction checks",`IMM_COUNT);
  $display("PASS: %0d reference-trace checks, 32 registers, 64 memory words, JAL loop and 9 fault cases",`TRACE_COUNT);
  $finish;
 end
 task check_fault(input [31:0] bad);
  begin
   reset=1;#1;dut.imem.mem[0]=bad;#1;reset=0;#1;
   if(!fault) $fatal(1,"Expected fault for %h",bad);
   @(posedge clk);#1;
   if(pc!==0 || dut.rf.regs[1]!==0 || dut.dmem.mem[0]!==0) $fatal(1,"Fault caused side effects");
   @(negedge clk);
  end
 endtask
 initial begin #20000;$fatal(1,"Simulation timeout");end
endmodule
`default_nettype wire

results/core.vcd
$date
	Thu Oct  8 10:21:05 2026
$end
$version
	Icarus Verilog
$end
$timescale
	1ps
$end
$scope module tb_single_cycle $end
$var wire 32 ! wb [31:0] $end
$var wire 1 " rw $end
$var wire 32 # probe_imm [31:0] $end
$var wire 32 $ pc [31:0] $end
$var wire 1 % mw $end
$var wire 32 & ins [31:0] $end
$var wire 1 ' fault $end
$var wire 1 ( bt $end
$var wire 32 ) alu [31:0] $end
$var reg 1 * clk $end
$var reg 32 + probe_ins [31:0] $end
$var reg 1 , reset $end
$var reg 256 - row [255:0] $end
$var integer 32 . i [31:0] $end
$scope module dut $end
$var wire 1 ( BranchTaken $end
$var wire 1 * clk $end
$var wire 1 ' fault $end
$var wire 1 , reset $end
$var wire 1 / zero $end
$var wire 32 0 writeback [31:0] $end
$var wire 1 1 use_imm $end
$var wire 32 2 target [31:0] $end
$var wire 32 3 next_pc [31:0] $end
$var wire 1 4 mem_to_reg $end
$var wire 1 5 mem_read $end
$var wire 1 6 mem_ok $end
$var wire 32 7 load_data [31:0] $end
$var wire 1 8 legal $end
$var wire 1 9 jump $end
$var wire 32 : instruction [31:0] $end
$var wire 32 ; imm [31:0] $end
$var wire 1 < if_ok $end
$var wire 1 = branch $end
$var wire 32 > b [31:0] $end
$var wire 4 ? alu_op [3:0] $end
$var wire 32 @ alu_b [31:0] $end
$var wire 32 A a [31:0] $end
$var wire 1 " RegWrite $end
$var wire 1 % MemWrite $end
$var wire 32 B ALU_Out [31:0] $end
$var parameter 32 C DMEM_WORDS $end
$var parameter 32 D IMEM_WORDS $end
$var parameter 168 E PROGRAM_FILE $end
$var reg 32 F PC [31:0] $end
$scope module alu $end
$var wire 32 G b [31:0] $end
$var wire 1 / zero $end
$var wire 4 H op [3:0] $end
$var wire 32 I a [31:0] $end
$var reg 32 J result [31:0] $end
$upscope $end
$scope module cu $end
$var wire 32 K ins [31:0] $end
$var reg 1 = branch $end
$var reg 1 9 jump $end
$var reg 1 8 legal $end
$var reg 1 5 mr $end
$var reg 1 4 mtr $end
$var reg 1 % mw $end
$var reg 4 L op [3:0] $end
$var reg 1 " rw $end
$var reg 1 1 src $end
$upscope $end
$scope module dmem $end
$var wire 32 M address [31:0] $end
$var wire 1 * clk $end
$var wire 1 5 re $end
$var wire 1 , reset $end
$var wire 1 6 valid $end
$var wire 1 N we $end
$var wire 32 O wd [31:0] $end
$var wire 32 P data [31:0] $end
$var parameter 32 Q WORDS $end
$var integer 32 R i [31:0] $end
$upscope $end
$scope module ig $end
$var wire 32 S ins [31:0] $end
$var reg 32 T imm [31:0] $end
$upscope $end
$scope module imem $end
$var wire 32 U address [31:0] $end
$var wire 1 < valid $end
$var wire 32 V instruction [31:0] $end
$var parameter 168 W PROGRAM_FILE $end
$var parameter 32 X WORDS $end
$upscope $end
$scope module rf $end
$var wire 1 * clk $end
$var wire 5 Y rd [4:0] $end
$var wire 1 , reset $end
$var wire 5 Z rs1 [4:0] $end
$var wire 5 [ rs2 [4:0] $end
$var wire 32 \ wd [31:0] $end
$var wire 1 ] we $end
$var wire 32 ^ b [31:0] $end
$var wire 32 _ a [31:0] $end
$var integer 32 ` i [31:0] $end
$upscope $end
$upscope $end
$scope module probe $end
$var wire 32 a ins [31:0] $end
$var reg 32 b imm [31:0] $end
$upscope $end
$scope task check_fault $end
$var reg 32 c bad [31:0] $end
$upscope $end
$upscope $end
$enddefinitions $end
$comment Show the parameter values. $end
$dumpall
b100000000 X
b11100110110100101101101001011110111000001110010011011110110011101110010011000010110110101110011001011110110010001100101011011010110111100101110011010000110010101111000 W
b1000000 Q
b11100110110100101101101001011110111000001110010011011110110011101110010011000010110110101110011001011110110010001100101011011010110111100101110011010000110010101111000 E
b100000000 D
b1000000 C
$end
#0
$dumpvars
bx c
bx b
b0 a
bx `
bx _
bx ^
x]
bx \
bx [
bx Z
bx Y
bx V
bx U
bx T
bx S
bx R
bx P
bx O
xN
bx M
bx L
bx K
bx J
bx I
bx H
bx G
bx F
bx B
bx A
bx @
bx ?
bx >
x=
x<
bx ;
bx :
x9
x8
bx 7
x6
x5
x4
bx 3
bx 2
x1
bx 0
x/
bx .
bx -
1,
b0 +
0*
bx )
x(
x'
bx &
x%
bx $
bx #
x"
bx !
$end
#5000
16
b1100 !
b1100 0
b1100 \
0/
b1100 )
b1100 B
b1100 J
b1100 M
b0 >
b0 O
b0 ^
b1100 @
b1100 G
0'
b0 7
b0 P
b0 A
b0 I
b0 _
0(
0N
1]
b100 3
b1 Y
b1100 [
b0 Z
18
b0 ?
b0 H
b0 L
09
0=
04
0%
05
11
1"
b1100 2
b1100 ;
b1100 T
1<
b110000000000000010010011 &
b110000000000000010010011 :
b110000000000000010010011 K
b110000000000000010010011 S
b110000000000000010010011 V
b0 $
b0 F
b0 U
b100000 `
b1000000 R
1*
#10000
0*
#12000
b100000000000000000000000000000000010000000000000000000000000000000100000000000000000000000000001100000000000000000000000000000000000000000000000000000000000000000000000000000000000000000000000000 -
b0 .
0,
#15000
06
b101 !
b101 0
b101 \
b101 )
b101 B
b101 J
b101 M
b101 @
b101 G
b10 Y
b101 [
18
11
1"
b101 ;
b101 T
b10100000000000100010011 &
b10100000000000100010011 :
b10100000000000100010011 K
b10100000000000100010011 S
b10100000000000100010011 V
b1000 3
b1001 2
b100 $
b100 F
b100 U
1*
#20000
b10000000000000000000000000000001000000000000000000000000000000000100000000000000000000000000000000100000000000000000000000000000101000000000000000000000000000000000000000000000000000000000000000000000000000000000000000000000000 -
b1 .
0*
#25000
b11111111111111111111111111111000 !
b11111111111111111111111111111000 0
b11111111111111111111111111111000 \
b11111111111111111111111111111000 )
b11111111111111111111111111111000 B
b11111111111111111111111111111000 J
b11111111111111111111111111111000 M
b11111111111111111111111111111000 @
b11111111111111111111111111111000 G
b11 Y
b11000 [
18
11
1"
b11111111111111111111111111111000 ;
b11111111111111111111111111111000 T
b11111111100000000000000110010011 &
b11111111100000000000000110010011 :
b11111111100000000000000110010011 K
b11111111100000000000000110010011 S
b11111111100000000000000110010011 V
b1100 3
b0 2
b1000 $
b1000 F
b1000 U
1*
#30000
b100000000000000000000000000000001100000000000000000000000000000000110000000000000000000000000000000111111111111111111111111111111000000000000000000000000000000000000000000000000000000000000000000000000000000000000000000000000000 -
b10 .
0*
#35000
06
b10001 !
b10001 0
b10001 \
b10001 )
b10001 B
b10001 J
b10001 M
b101 >
b101 O
b101 ^
b1100 A
b1100 I
b1100 _
b101 @
b101 G
b100 Y
b10 [
b1 Z
18
01
1"
b0 ;
b0 T
b1000001000001000110011 &
b1000001000001000110011 :
b1000001000001000110011 K
b1000001000001000110011 S
b1000001000001000110011 V
b10000 3
b1100 2
b1100 $
b1100 F
b1100 U
1*
#40000
b110000000000000000000000000000010000000000000000000000000000000001000000000000000000000000000000000100000000000000000000000000010001000000000000000000000000000000000000000000000000000000000000000000000000000000000000000000000000 -
b11 .
0*
#45000
b111 !
b111 0
b111 \
b111 )
b111 B
b111 J
b111 M
b1 ?
b1 H
b1 L
18
1"
b1000000001000001000001000110011 &
b1000000001000001000001000110011 :
b1000000001000001000001000110011 K
b1000000001000001000001000110011 S
b1000000001000001000001000110011 V
b10100 3
b10000 2
b10000 $
b10000 F
b10000 U
1*
#50000
b1000000000000000000000000000000010100000000000000000000000000000001000000000000000000000000000000000100000000000000000000000000000111000000000000000000000000000000000000000000000000000000000000000000000000000000000000000000000000 -
b100 .
0*
#55000
16
b100 !
b100 0
b100 \
b100 )
b100 B
b100 J
b100 M
18
b10 ?
b10 H
b10 L
1"
b1000001111001000110011 &
b1000001111001000110011 :
b1000001111001000110011 K
b1000001111001000110011 S
b1000001111001000110011 V
b11000 3
b10100 2
b10100 $
b10100 F
b10100 U
1*
#60000
b1010000000000000000000000000000011000000000000000000000000000000001000000000000000000000000000000000100000000000000000000000000000100000000000000000000000000000000000000000000000000000000000000000000000000000000000000000000000000 -
b101 .
0*
#65000
06
b1101 !
b1101 0
b1101 \
b1101 )
b1101 B
b1101 J
b1101 M
18
b11 ?
b11 H
b11 L
1"
b1000001110001000110011 &
b1000001110001000110011 :
b1000001110001000110011 K
b1000001110001000110011 S
b1000001110001000110011 V
b11100 3
b11000 2
b11000 $
b11000 F
b11000 U
1*
#70000
b1100000000000000000000000000000011100000000000000000000000000000001000000000000000000000000000000000100000000000000000000000000001101000000000000000000000000000000000000000000000000000000000000000000000000000000000000000000000000 -
b110 .
0*
#75000
b1001 !
b1001 0
b1001 \
b1001 )
b1001 B
b1001 J
b1001 M
18
b100 ?
b100 H
b100 L
1"
b1000001100001000110011 &
b1000001100001000110011 :
b1000001100001000110011 K
b1000001100001000110011 S
b1000001100001000110011 V
b100000 3
b11100 2
b11100 $
b11100 F
b11100 U
1*
#80000
b1110000000000000000000000000000100000000000000000000000000000000001000000000000000000000000000000000100000000000000000000000000001001000000000000000000000000000000000000000000000000000000000000000000000000000000000000000000000000 -
b111 .
0*
#85000
b110000000 !
b110000000 0
b110000000 \
b110000000 )
b110000000 B
b110000000 J
b110000000 M
18
b101 ?
b101 H
b101 L
1"
b1000001001001000110011 &
b1000001001001000110011 :
b1000001001001000110011 K
b1000001001001000110011 S
b1000001001001000110011 V
b100100 3
b100000 2
b100000 $
b100000 F
b100000 U
1*
#90000
b10000000000000000000000000000000100100000000000000000000000000000001000000000000000000000000000000000100000000000000000000000110000000000000000000000000000000000000000000000000000000000000000000000000000000000000000000000000000000 -
b1000 .
0*
#95000
16
b0 !
b0 0
b0 \
1/
b0 )
b0 B
b0 J
b0 M
18
b110 ?
b110 H
b110 L
1"
b1000001101001000110011 &
b1000001101001000110011 :
b1000001101001000110011 K
b1000001101001000110011 S
b1000001101001000110011 V
b101000 3
b100100 2
b100100 $
b100100 F
b100100 U
1*
#100000
b10010000000000000000000000000000101000000000000000000000000000000001000000000000000000000000000000000100000000000000000000000000000000000000000000000000000000000000000000000000000000000000000000000000000000000000000000000000000000 -
b1001 .
0*
#105000
18
b111 ?
b111 H
b111 L
1"
b1000000001000001101001000110011 &
b1000000001000001101001000110011 :
b1000000001000001101001000110011 K
b1000000001000001101001000110011 S
b1000000001000001101001000110011 V
b101100 3
b101000 2
b101000 $
b101000 F
b101000 U
1*
#110000
b10100000000000000000000000000000101100000000000000000000000000000001000000000000000000000000000000000100000000000000000000000000000000000000000000000000000000000000000000000000000000000000000000000000000000000000000000000000000000 -
b1010 .
0*
#115000
18
b1000 ?
b1000 H
b1000 L
1"
b1000001010001000110011 &
b1000001010001000110011 :
b1000001010001000110011 K
b1000001010001000110011 S
b1000001010001000110011 V
b110000 3
b101100 2
b101100 $
b101100 F
b101100 U
1*
#120000
b10110000000000000000000000000000110000000000000000000000000000000001000000000000000000000000000000000100000000000000000000000000000000000000000000000000000000000000000000000000000000000000000000000000000000000000000000000000000000 -
b1011 .
0*
#125000
18
b1001 ?
b1001 H
b1001 L
1"
b1000001011001000110011 &
b1000001011001000110011 :
b1000001011001000110011 K
b1000001011001000110011 S
b1000001011001000110011 V
b110100 3
b110000 2
b110000 $
b110000 F
b110000 U
1*
#130000
b11000000000000000000000000000000110100000000000000000000000000000001000000000000000000000000000000000100000000000000000000000000000000000000000000000000000000000000000000000000000000000000000000000000000000000000000000000000000000 -
b1100 .
0*
#135000
06
b11111111111111111111111111110111 !
b11111111111111111111111111110111 0
b11111111111111111111111111110111 \
b0 >
b0 O
b0 ^
b11111111111111111111111111111000 A
b11111111111111111111111111111000 I
b11111111111111111111111111111000 _
b11111111111111111111111111111111 @
b11111111111111111111111111111111 G
0/
b11111111111111111111111111110111 )
b11111111111111111111111111110111 B
b11111111111111111111111111110111 J
b11111111111111111111111111110111 M
b101 Y
b11111 [
b11 Z
11
18
b0 ?
b0 H
b0 L
1"
b11111111111111111111111111111111 ;
b11111111111111111111111111111111 T
b11111111111100011000001010010011 &
b11111111111100011000001010010011 :
b11111111111100011000001010010011 K
b11111111111100011000001010010011 S
b11111111111100011000001010010011 V
b111000 3
b110011 2
b110100 $
b110100 F
b110100 U
1*
#140000
b11010000000000000000000000000000111000000000000000000000000000000001010000000000000000000000000000000111111111111111111111111111110111000000000000000000000000000000000000000000000000000000000000000000000000000000000000000000000000 -
b1101 .
0*
#145000
b11111111111111111111111111111000 !
b11111111111111111111111111111000 0
b11111111111111111111111111111000 \
b11111111111111111111111111111000 )
b11111111111111111111111111111000 B
b11111111111111111111111111111000 J
b11111111111111111111111111111000 M
b10 ?
b10 H
b10 L
18
11
1"
b11111111111111111111111111111111 ;
b11111111111111111111111111111111 T
b11111111111100011111001010010011 &
b11111111111100011111001010010011 :
b11111111111100011111001010010011 K
b11111111111100011111001010010011 S
b11111111111100011111001010010011 V
b111100 3
b110111 2
b111000 $
b111000 F
b111000 U
1*
#150000
b11100000000000000000000000000000111100000000000000000000000000000001010000000000000000000000000000000111111111111111111111111111111000000000000000000000000000000000000000000000000000000000000000000000000000000000000000000000000000 -
b1110 .
0*
#155000
b11111111111111111111111111111111 !
b11111111111111111111111111111111 0
b11111111111111111111111111111111 \
b11111111111111111111111111111111 )
b11111111111111111111111111111111 B
b11111111111111111111111111111111 J
b11111111111111111111111111111111 M
18
b11 ?
b11 H
b11 L
11
1"
b11111111111111111111111111111111 ;
b11111111111111111111111111111111 T
b11111111111100011110001010010011 &
b11111111111100011110001010010011 :
b11111111111100011110001010010011 K
b11111111111100011110001010010011 S
b11111111111100011110001010010011 V
b1000000 3
b111011 2
b111100 $
b111100 F
b111100 U
1*
#160000
b11110000000000000000000000000001000000000000000000000000000000000001010000000000000000000000000000000111111111111111111111111111111111000000000000000000000000000000000000000000000000000000000000000000000000000000000000000000000000 -
b1111 .
0*
#165000
b111 !
b111 0
b111 \
b111 )
b111 B
b111 J
b111 M
18
b100 ?
b100 H
b100 L
11
1"
b11111111111111111111111111111111 ;
b11111111111111111111111111111111 T
b11111111111100011100001010010011 &
b11111111111100011100001010010011 :
b11111111111100011100001010010011 K
b11111111111100011100001010010011 S
b11111111111100011100001010010011 V
b1000100 3
b111111 2
b1000000 $
b1000000 F
b1000000 U
1*
#170000
b100000000000000000000000000000001000100000000000000000000000000000001010000000000000000000000000000000100000000000000000000000000000111000000000000000000000000000000000000000000000000000000000000000000000000000000000000000000000000 -
b10000 .
0*
#175000
b11111111111111111111111111000000 !
b11111111111111111111111111000000 0
b11111111111111111111111111000000 \
b11111111111111111111111111111000 >
b11111111111111111111111111111000 O
b11111111111111111111111111111000 ^
b11111111111111111111111111000000 )
b11111111111111111111111111000000 B
b11111111111111111111111111000000 J
b11111111111111111111111111000000 M
b11 @
b11 G
b11 [
18
b101 ?
b101 H
b101 L
11
1"
b11 ;
b11 T
b1100011001001010010011 &
b1100011001001010010011 :
b1100011001001010010011 K
b1100011001001010010011 S
b1100011001001010010011 V
b1001000 3
b1000111 2
b1000100 $
b1000100 F
b1000100 U
1*
#180000
b100010000000000000000000000000001001000000000000000000000000000000001010000000000000000000000000000000111111111111111111111111111000000000000000000000000000000000000000000000000000000000000000000000000000000000000000000000000000000 -
b10001 .
0*
#185000
b11111111111111111111111111111 !
b11111111111111111111111111111 0
b11111111111111111111111111111 \
b11111111111111111111111111111 )
b11111111111111111111111111111 B
b11111111111111111111111111111 J
b11111111111111111111111111111 M
18
b110 ?
b110 H
b110 L
11
1"
b11 ;
b11 T
b1100011101001010010011 &
b1100011101001010010011 :
b1100011101001010010011 K
b1100011101001010010011 S
b1100011101001010010011 V
b1001100 3
b1001011 2
b1001000 $
b1001000 F
b1001000 U
1*
#190000
b100100000000000000000000000000001001100000000000000000000000000000001010000000000000000000000000000000100011111111111111111111111111111000000000000000000000000000000000000000000000000000000000000000000000000000000000000000000000000 -
b10010 .
0*
#195000
b11111111111111111111111111111111 !
b11111111111111111111111111111111 0
b11111111111111111111111111111111 \
b11111111111111111111111111111111 )
b11111111111111111111111111111111 B
b11111111111111111111111111111111 J
b11111111111111111111111111111111 M
b10000000011 @
b10000000011 G
18
b111 ?
b111 H
b111 L
11
1"
b10000000011 ;
b10000000011 T
b1000000001100011101001010010011 &
b1000000001100011101001010010011 :
b1000000001100011101001010010011 K
b1000000001100011101001010010011 S
b1000000001100011101001010010011 V
b1010000 3
b10001001111 2
b1001100 $
b1001100 F
b1001100 U
1*
#200000
b100110000000000000000000000000001010000000000000000000000000000000001010000000000000000000000000000000111111111111111111111111111111111000000000000000000000000000000000000000000000000000000000000000000000000000000000000000000000000 -
b10011 .
0*
#205000
b1 !
b1 0
b1 \
b0 >
b0 O
b0 ^
b1 )
b1 B
b1 J
b1 M
b11111111111111111111111111111111 @
b11111111111111111111111111111111 G
b11111 [
18
b1000 ?
b1000 H
b1000 L
11
1"
b11111111111111111111111111111111 ;
b11111111111111111111111111111111 T
b11111111111100011010001010010011 &
b11111111111100011010001010010011 :
b11111111111100011010001010010011 K
b11111111111100011010001010010011 S
b11111111111100011010001010010011 V
b1010100 3
b1001111 2
b1010000 $
b1010000 F
b1010000 U
1*
#210000
b101000000000000000000000000000001010100000000000000000000000000000001010000000000000000000000000000000100000000000000000000000000000001000000000000000000000000000000000000000000000000000000000000000000000000000000000000000000000000 -
b10100 .
0*
#215000
18
b1001 ?
b1001 H
b1001 L
11
1"
b11111111111111111111111111111111 ;
b11111111111111111111111111111111 T
b11111111111100011011001010010011 &
b11111111111100011011001010010011 :
b11111111111100011011001010010011 K
b11111111111100011011001010010011 S
b11111111111100011011001010010011 V
b1011000 3
b1010011 2
b1010100 $
b1010100 F
b1010100 U
1*
#220000
b101010000000000000000000000000001011000000000000000000000000000000001010000000000000000000000000000000100000000000000000000000000000001000000000000000000000000000000000000000000000000000000000000000000000000000000000000000000000000 -
b10101 .
0*
#225000
b11111111111111111111111111111111 !
b11111111111111111111111111111111 0
b11111111111111111111111111111111 \
b101 >
b101 O
b101 ^
b11111111111111111111111111111111 )
b11111111111111111111111111111111 B
b11111111111111111111111111111111 J
b11111111111111111111111111111111 M
b101 @
b101 G
b110 Y
b10 [
18
b111 ?
b111 H
b111 L
01
1"
b0 ;
b0 T
b1000000001000011101001100110011 &
b1000000001000011101001100110011 :
b1000000001000011101001100110011 K
b1000000001000011101001100110011 S
b1000000001000011101001100110011 V
b1011100 3
b1011000 2
b1011000 $
b1011000 F
b1011000 U
1*
#230000
b101100000000000000000000000000001011100000000000000000000000000000001100000000000000000000000000000000111111111111111111111111111111111000000000000000000000000000000000000000000000000000000000000000000000000000000000000000000000000 -
b10110 .
0*
#235000
b111111111111111111111111111 !
b111111111111111111111111111 0
b111111111111111111111111111 \
b111111111111111111111111111 )
b111111111111111111111111111 B
b111111111111111111111111111 J
b111111111111111111111111111 M
b111 Y
18
b110 ?
b110 H
b110 L
1"
b1000011101001110110011 &
b1000011101001110110011 :
b1000011101001110110011 K
b1000011101001110110011 S
b1000011101001110110011 V
b1100000 3
b1011100 2
b1011100 $
b1011100 F
b1011100 U
1*
#240000
b101110000000000000000000000000001100000000000000000000000000000000001110000000000000000000000000000000100000111111111111111111111111111000000000000000000000000000000000000000000000000000000000000000000000000000000000000000000000000 -
b10111 .
0*
#245000
b1 !
b1 0
b1 \
b1100 @
b1100 G
b1100 >
b1100 O
b1100 ^
b1 )
b1 B
b1 J
b1 M
b1000 Y
b1 [
18
b1000 ?
b1000 H
b1000 L
1"
b100011010010000110011 &
b100011010010000110011 :
b100011010010000110011 K
b100011010010000110011 S
b100011010010000110011 V
b1100100 3
b1100000 2
b1100000 $
b1100000 F
b1100000 U
1*
#250000
b110000000000000000000000000000001100100000000000000000000000000000010000000000000000000000000000000000100000000000000000000000000000001000000000000000000000000000000000000000000000000000000000000000000000000000000000000000000000000 -
b11000 .
0*
#255000
16
b0 !
b0 0
b0 \
1/
b0 )
b0 B
b0 J
b0 M
b1001 Y
18
b1001 ?
b1001 H
b1001 L
1"
b100011011010010110011 &
b100011011010010110011 :
b100011011010010110011 K
b100011011010010110011 S
b100011011010010110011 V
b1101000 3
b1100100 2
b1100100 $
b1100100 F
b1100100 U
1*
#260000
b110010000000000000000000000000001101000000000000000000000000000000010010000000000000000000000000000000100000000000000000000000000000000000000000000000000000000000000000000000000000000000000000000000000000000000000000000000000000000 -
b11001 .
0*
#265000
b0 !
b0 0
b0 \
b0 A
b0 I
b0 _
1N
b0 @
b0 G
1/
b0 )
b0 B
b0 J
b0 M
0]
b0 Y
b0 Z
1%
11
18
b0 ?
b0 H
b0 L
0"
b100000010000000100011 &
b100000010000000100011 :
b100000010000000100011 K
b100000010000000100011 S
b100000010000000100011 V
b1101100 3
b1101000 2
b1101000 $
b1101000 F
b1101000 U
1*
#270000
b110100000000000000000000000000001101100000000000000000000000000000000010000000000000000000000000000000000000000000000000000000000000000000000000000000000000000000000010000000000000000000000000000000000000000000000000000000000001100 -
b11010 .
0*
